[
  {
    "id": "flt-00",
    "familyId": "kumaran",
    "cabin": "Economy",
    "stops": "Nonstop",
    "totalPrice": 1640,
    "perTravelerPrice": 410,
    "carrierLabel": "Delta",
    "durationLabel": "1h 58m",
    "departSummary": "DTW -> AVL, Wed Nov 25",
    "returnSummary": "AVL -> DTW, Sun Nov 29",
    "bookingUrl": "https://www.google.com/travel/flights",
    "sourceLabel": "Google Flights"
  },
  {
    "id": "flt-01",
    "familyId": "kumaran",
    "cabin": "Economy",
    "stops": "1-stop",
    "totalPrice": 1460,
    "perTravelerPrice": 365,
    "carrierLabel": "Delta + American",
    "durationLabel": "6h 35m",
    "departSummary": "DTW -> AVL, Wed Nov 25",
    "returnSummary": "AVL -> DTW, Sun Nov 29",
    "bookingUrl": "https://www.google.com/travel/flights",
    "sourceLabel": "Google Flights"
  },
  {
    "id": "flt-01b",
    "familyId": "kumaran",
    "cabin": "Economy Plus",
    "stops": "Nonstop",
    "totalPrice": 2140,
    "perTravelerPrice": 535,
    "carrierLabel": "Delta Comfort+",
    "durationLabel": "1h 58m",
    "departSummary": "DTW -> AVL, Wed Nov 25",
    "returnSummary": "AVL -> DTW, Sun Nov 29",
    "bookingUrl": "https://www.google.com/travel/flights",
    "sourceLabel": "Google Flights"
  },
  {
    "id": "flt-02",
    "familyId": "kumaran",
    "cabin": "Economy Plus",
    "stops": "1-stop",
    "totalPrice": 1980,
    "perTravelerPrice": 495,
    "carrierLabel": "Delta Comfort+ mix",
    "durationLabel": "6h 18m",
    "departSummary": "DTW -> AVL, Wed Nov 25",
    "returnSummary": "AVL -> DTW, Sun Nov 29",
    "bookingUrl": "https://www.google.com/travel/flights",
    "sourceLabel": "Google Flights"
  },
  {
    "id": "flt-03",
    "familyId": "chandrasekaran",
    "cabin": "Economy",
    "stops": "1-stop",
    "totalPrice": 1920,
    "perTravelerPrice": 480,
    "carrierLabel": "United",
    "durationLabel": "8h 52m",
    "departSummary": "SFO -> AVL, Wed Nov 25",
    "returnSummary": "AVL -> SFO, Sun Nov 29",
    "bookingUrl": "https://www.google.com/travel/flights",
    "sourceLabel": "Google Flights"
  },
  {
    "id": "flt-04",
    "familyId": "chandrasekaran",
    "cabin": "Economy Plus",
    "stops": "1-stop",
    "totalPrice": 2660,
    "perTravelerPrice": 665,
    "carrierLabel": "United Economy Plus",
    "durationLabel": "8h 44m",
    "departSummary": "SFO -> AVL, Wed Nov 25",
    "returnSummary": "AVL -> SFO, Sun Nov 29",
    "bookingUrl": "https://www.google.com/travel/flights",
    "sourceLabel": "Google Flights"
  },
  {
    "id": "flt-05",
    "familyId": "vaithilingam",
    "cabin": "Economy",
    "stops": "1-stop",
    "totalPrice": 1880,
    "perTravelerPrice": 470,
    "carrierLabel": "Southwest + American",
    "durationLabel": "9h 05m",
    "departSummary": "OAK -> AVL, Wed Nov 25",
    "returnSummary": "AVL -> OAK, Sun Nov 29",
    "bookingUrl": "https://www.google.com/travel/flights",
    "sourceLabel": "Google Flights"
  },
  {
    "id": "flt-06",
    "familyId": "vaithilingam",
    "cabin": "Economy Plus",
    "stops": "1-stop",
    "totalPrice": 2520,
    "perTravelerPrice": 630,
    "carrierLabel": "American Main Cabin Extra",
    "durationLabel": "8h 40m",
    "departSummary": "OAK -> AVL, Wed Nov 25",
    "returnSummary": "AVL -> OAK, Sun Nov 29",
    "bookingUrl": "https://www.google.com/travel/flights",
    "sourceLabel": "Google Flights"
  },
  {
    "id": "flt-07",
    "familyId": "ajagane",
    "cabin": "Economy",
    "stops": "1-stop",
    "totalPrice": 1440,
    "perTravelerPrice": 480,
    "carrierLabel": "United",
    "durationLabel": "8h 47m",
    "departSummary": "SFO -> AVL, Wed Nov 25",
    "returnSummary": "AVL -> SFO, Sun Nov 29",
    "bookingUrl": "https://www.google.com/travel/flights",
    "sourceLabel": "Google Flights"
  },
  {
    "id": "flt-08",
    "familyId": "ajagane",
    "cabin": "Economy Plus",
    "stops": "1-stop",
    "totalPrice": 1995,
    "perTravelerPrice": 665,
    "carrierLabel": "United Economy Plus",
    "durationLabel": "8h 38m",
    "departSummary": "SFO -> AVL, Wed Nov 25",
    "returnSummary": "AVL -> SFO, Sun Nov 29",
    "bookingUrl": "https://www.google.com/travel/flights",
    "sourceLabel": "Google Flights"
  },
  {
    "id": "flt-09",
    "familyId": "venkatesan-i",
    "cabin": "Economy",
    "stops": "1-stop",
    "totalPrice": 1730,
    "perTravelerPrice": 432.5,
    "carrierLabel": "Alaska + American",
    "durationLabel": "8h 11m",
    "departSummary": "SEA -> AVL, Wed Nov 25",
    "returnSummary": "AVL -> SEA, Sun Nov 29",
    "bookingUrl": "https://www.google.com/travel/flights",
    "sourceLabel": "Google Flights"
  },
  {
    "id": "flt-10",
    "familyId": "venkatesan-i",
    "cabin": "Economy Plus",
    "stops": "1-stop",
    "totalPrice": 2350,
    "perTravelerPrice": 587.5,
    "carrierLabel": "Alaska Premium / Delta Comfort+",
    "durationLabel": "7h 58m",
    "departSummary": "SEA -> AVL, Wed Nov 25",
    "returnSummary": "AVL -> SEA, Sun Nov 29",
    "bookingUrl": "https://www.google.com/travel/flights",
    "sourceLabel": "Google Flights"
  },
  {
    "id": "flt-10b",
    "familyId": "venkatesan-ii",
    "cabin": "Economy",
    "stops": "1-stop",
    "totalPrice": 1180,
    "perTravelerPrice": 295,
    "carrierLabel": "American",
    "durationLabel": "4h 21m",
    "departSummary": "ORD -> AVL, Wed Nov 25",
    "returnSummary": "AVL -> ORD, Sun Nov 29",
    "bookingUrl": "https://www.google.com/travel/flights",
    "sourceLabel": "Google Flights"
  },
  {
    "id": "flt-11",
    "familyId": "venkatesan-ii",
    "cabin": "Economy",
    "stops": "Nonstop",
    "totalPrice": 1320,
    "perTravelerPrice": 330,
    "carrierLabel": "Allegiant / American mix",
    "durationLabel": "2h 01m",
    "departSummary": "ORD -> AVL, Wed Nov 25",
    "returnSummary": "AVL -> ORD, Sun Nov 29",
    "bookingUrl": "https://www.google.com/travel/flights",
    "sourceLabel": "Google Flights"
  },
  {
    "id": "flt-11b",
    "familyId": "venkatesan-ii",
    "cabin": "Economy Plus",
    "stops": "1-stop",
    "totalPrice": 1590,
    "perTravelerPrice": 397.5,
    "carrierLabel": "American Main Cabin Extra",
    "durationLabel": "4h 15m",
    "departSummary": "ORD -> AVL, Wed Nov 25",
    "returnSummary": "AVL -> ORD, Sun Nov 29",
    "bookingUrl": "https://www.google.com/travel/flights",
    "sourceLabel": "Google Flights"
  },
  {
    "id": "flt-12",
    "familyId": "venkatesan-ii",
    "cabin": "Economy Plus",
    "stops": "Nonstop",
    "totalPrice": 1780,
    "perTravelerPrice": 445,
    "carrierLabel": "American Main Cabin Extra",
    "durationLabel": "2h 01m",
    "departSummary": "ORD -> AVL, Wed Nov 25",
    "returnSummary": "AVL -> ORD, Sun Nov 29",
    "bookingUrl": "https://www.google.com/travel/flights",
    "sourceLabel": "Google Flights"
  }
]
